{
  "seo": {
    "title": "Careers | HeartLink",
    "description": "Join HeartLink's private matchmaking team."
  },
  "hero": {
    "eyebrow": "Careers at HeartLink",
    "title": "Work that needs <em>trust.</em>",
    "description": "We look for people with maturity, good judgment, strong communication and complete respect for privacy."
  },
  "cta": {
    "primaryLabel": "Introduce Yourself",
    "primaryUrl": "mailto:careers@heartlink.in?subject=Confidential%20Expression%20of%20Interest",
    "showWhatsapp": false,
    "whatsappLabel": "Quick WhatsApp Enquiry"
  },
  "rolesIntro": {
    "eyebrow": "The standard",
    "title": "Work that needs trust and maturity.",
    "description": "HeartLink is not a volume business. Every team member handles private family information. We value good communication, cultural understanding, mature judgment and privacy."
  },
  "roles": [
    { "title": "Senior Relationship Manager", "details": "Mumbai · Hybrid · 8+ years in private client, luxury or advisory services" },
    { "title": "Network Scout", "details": "Global · Flexible · Strong social intelligence and trusted networks" },
    { "title": "Relationship Advisor", "details": "India · Consulting · Couple or family guidance experience" },
    { "title": "Private Office Associate", "details": "Mumbai · Full-time · High-touch operations and strict confidentiality" }
  ],
  "culture": {
    "eyebrow": "Our culture",
    "title": "Small team. High standards.",
    "description": "We work carefully, privately and without pressure. The goal is a good match, not a fast match.",
    "cards": [
      { "label": "01", "title": "Privacy is serious.", "description": "Every message, meeting and introduction must protect the client." },
      { "label": "02", "title": "Quality over speed.", "description": "We prefer fewer, better introductions." },
      { "label": "03", "title": "Warm but honest.", "description": "Clients should feel respected and clearly guided." }
    ]
  },
  "closing": {
    "eyebrow": "Careers",
    "quote": "Good people may not always fit an open role, but we are happy to hear from them.",
    "button": "Introduce Yourself"
  }
}
